{ "posts": [{
    "author": "James Higgins",
    "image": "http://roamersrestrvpark.com/wp-content/uploads/2015/03/roamers_rest_map.jpg",
    "location": "Campsite 1",
    "content": "This is my favorite campsite",
    "category": "Category 1"
  }, {
    "author": "James Higgins",
    "image": "http://roamersrestrvpark.com/wp-content/uploads/2015/03/roamers_rest_map.jpg",
    "location": "Campsite 1",
    "content": "This is my favorite campsite",
    "category": "Category 1"
  }, {
    "author": "James Higgins",
    "image": "http://roamersrestrvpark.com/wp-content/uploads/2015/03/roamers_rest_map.jpg",
    "location": "Campsite 1",
    "content": "This is my favorite campsite",
    "category": "Category 1"
    }],
    "comments": [{
      "author": "Andrea",
      "rating": 4,
      "content": "Did not fall down."
    }, {
      "author": "Alex",
      "rating": 9,
      "content": "Nice view of the volcano!"
    }]
  }
